nicegui_number_place/__init__.py
nicegui_number_place/number_place.py
nicegui_number_place/py.typed
nicegui_number_place/problem/data000.txt
nicegui_number_place/problem/data001.txt
nicegui_number_place/problem/data002.txt
nicegui_number_place/problem/data003.txt
nicegui_number_place/problem/data004.txt
nicegui_number_place/problem/data005.txt
nicegui_number_place/problem/data006.txt
nicegui_number_place/problem/data007.txt
nicegui_number_place/problem/data008.txt
nicegui_number_place/problem/data009.txt
nicegui_number_place/problem/data010.txt
nicegui_number_place/problem/data011.txt
nicegui_number_place/problem/data012.txt
nicegui_number_place/problem/data013.txt
nicegui_number_place/problem/data014.txt
nicegui_number_place/problem/data015.txt
nicegui_number_place/problem/data016.txt
nicegui_number_place/problem/data017.txt
nicegui_number_place/problem/data018.txt
nicegui_number_place/problem/data019.txt
nicegui_number_place/problem/data020.txt
nicegui_number_place/problem/data021.txt
nicegui_number_place/problem/data022.txt
nicegui_number_place/problem/data023.txt
nicegui_number_place/problem/data024.txt
nicegui_number_place/problem/data025.txt
nicegui_number_place/problem/data026.txt
nicegui_number_place/problem/data027.txt
nicegui_number_place/problem/data028.txt
nicegui_number_place/problem/data029.txt
nicegui_number_place/problem/data030.txt
nicegui_number_place/problem/data031.txt
nicegui_number_place/problem/data032.txt
nicegui_number_place/problem/data033.txt
nicegui_number_place/problem/data034.txt
nicegui_number_place/problem/data035.txt
nicegui_number_place/problem/data036.txt
nicegui_number_place/problem/data037.txt
nicegui_number_place/problem/data038.txt
nicegui_number_place/problem/data039.txt
nicegui_number_place/problem/data040.txt
nicegui_number_place/problem/data041.txt
nicegui_number_place/problem/data042.txt
nicegui_number_place/problem/data043.txt
nicegui_number_place/problem/data044.txt
nicegui_number_place/problem/data045.txt
nicegui_number_place-0.1.3.dist-info/METADATA
nicegui_number_place-0.1.3.dist-info/WHEEL
nicegui_number_place-0.1.3.dist-info/entry_points.txt
nicegui_number_place-0.1.3.dist-info/licenses/LICENSE
nicegui_number_place-0.1.3.dist-info/RECORD
