Metadata-Version: 2.4
Name: nicegui-number_place
Version: 0.1.3
Summary: Number Place puzzle on NiceGUI
Project-URL: homepage, https://github.com/SaitoTsutomu/nicegui-number_place
Author-email: Saito Tsutomu <tsutomu7@hotmail.co.jp>
License: Apache-2.0
License-File: LICENSE
Classifier: Development Status :: 1 - Planning
Classifier: License :: OSI Approved :: Apache Software License
Classifier: Programming Language :: Python
Classifier: Topic :: Scientific/Engineering
Classifier: Topic :: Software Development
Requires-Python: >=3.12
Requires-Dist: fire>=0.7.0
Requires-Dist: nicegui>=2.11.1
Requires-Dist: numpy>=2.2.3
